blockhouse/__init__.py
blockhouse/client.py
blockhouse/exceptions.py
blockhouse/s3_connector.py
blockhouse/usage.py
tests/__init__.py
tests/test_client.py
blockhouse_client-0.1.1.dist-info/METADATA
blockhouse_client-0.1.1.dist-info/WHEEL
blockhouse_client-0.1.1.dist-info/top_level.txt
blockhouse_client-0.1.1.dist-info/RECORD
